flask_lt.py
flask_localtunnel-1.0.6.dist-info/LICENSE
flask_localtunnel-1.0.6.dist-info/METADATA
flask_localtunnel-1.0.6.dist-info/WHEEL
flask_localtunnel-1.0.6.dist-info/top_level.txt
flask_localtunnel-1.0.6.dist-info/RECORD
