Metadata-Version: 2.1
Name: flask-localtunnel
Version: 1.0.6
Summary: A simple way to demo Flask apps from your machine.
Home-page: https://github.com/redevil1/flask-localtunnel
Author: Jak Bin
Keywords: flask,flask-ngrok,ngrok,localtunnel,demo
Classifier: Programming Language :: Python :: 3.6
Classifier: License :: OSI Approved :: Apache Software License
Classifier: Operating System :: OS Independent
License-File: LICENSE
Requires-Dist: Flask (>=0.14.0)
Requires-Dist: py-localtunnel
